gitcopilot-0.1.1.dist-info/licenses/LICENSE
gitpilot/__init__.py
gitpilot/agent_tools.py
gitpilot/agentic.py
gitpilot/api.py
gitpilot/cli.py
gitpilot/github_api.py
gitpilot/langflow_client.py
gitpilot/llm_provider.py
gitpilot/py.typed
gitpilot/settings.py
gitpilot/version.py
gitpilot/web/index.html
gitpilot/web/assets/index-9w27hobx.js
gitpilot/web/assets/index-a5ofe7cN.css
gitcopilot-0.1.1.dist-info/METADATA
gitcopilot-0.1.1.dist-info/WHEEL
gitcopilot-0.1.1.dist-info/entry_points.txt
gitcopilot-0.1.1.dist-info/top_level.txt
gitcopilot-0.1.1.dist-info/RECORD
