Metadata-Version: 2.4
Name: gitcopilot
Version: 0.1.1
Summary: Production-ready agentic AI assistant for GitHub repositories with multi-LLM support and visual workflow insights
Author: Ruslan Magana Vsevolodovna
License-Expression: MIT
Project-URL: Homepage, https://github.com/ruslanmv/gitpilot
Project-URL: Documentation, https://github.com/ruslanmv/gitpilot#readme
Project-URL: Repository, https://github.com/ruslanmv/gitpilot
Project-URL: Issues, https://github.com/ruslanmv/gitpilot/issues
Keywords: ai,github,copilot,agentic,crewai,llm,openai,claude,watsonx,ollama,fastapi,react
Classifier: Development Status :: 4 - Beta
Classifier: Intended Audience :: Developers
Classifier: Programming Language :: Python :: 3
Classifier: Programming Language :: Python :: 3.11
Classifier: Programming Language :: JavaScript
Classifier: Framework :: FastAPI
Classifier: Topic :: Software Development :: Libraries :: Python Modules
Classifier: Topic :: Software Development :: Version Control :: Git
Classifier: Topic :: Scientific/Engineering :: Artificial Intelligence
Classifier: Operating System :: OS Independent
Requires-Python: <3.12,>=3.11
License-File: LICENSE
Requires-Dist: fastapi>=0.111.0
Requires-Dist: uvicorn[standard]>=0.30.0
Requires-Dist: httpx>=0.27.0
Requires-Dist: python-dotenv>=1.1.0
Requires-Dist: typer>=0.12.0
Requires-Dist: pydantic>=2.7.0
Requires-Dist: crewai>=0.76.9
Requires-Dist: crewai-tools>=0.13.4
Requires-Dist: ibm-watsonx-ai>=1.1.0
Requires-Dist: langchain-ibm>=0.3.0
Requires-Dist: rich>=13.0.0
Provides-Extra: dev
Requires-Dist: ruff>=0.6; extra == "dev"
Requires-Dist: pytest>=8.2; extra == "dev"
Requires-Dist: build>=1.2.1; extra == "dev"
Requires-Dist: twine>=5.0.0; extra == "dev"
Dynamic: license-file
